DIGITAL_SYSTEM_LAB/lab3/Q4/q4.v
module q4(a,b,c,d,f);
input a,b,c,d;
output f;
assign f=(~a|~d)&(~b|d);
endmodule

DIGITAL_SYSTEM_LAB/lab3/Q4/q4_tb.v
`timescale 1ns/1ns
`include "q4.v"
module q4_tb();
reg a,b,c,d;
wire f;
q4 q1(a,b,c,d,f);
initial
begin
  $dumpfile("q4_tb.vcd");
  $dumpvars(0,q4_tb);
a=1'b0;b=1'b0;c=1'b0;d=1'b0;
#20  
a=1'b0;b=1'b0;c=1'b0;d=1'b1;
#20  
a=1'b0;b=1'b0;c=1'b1;d=1'b0;
#20  
a=1'b0;b=1'b0;c=1'b1;d=1'b1;
#20  
a=1'b0;b=1'b1;c=1'b0;d=1'b0;
#20  
a=1'b0;b=1'b1;c=1'b0;d=1'b1;
#20  
a=1'b0;b=1'b1;c=1'b1;d=1'b0;
#20  
a=1'b0;b=1'b1;c=1'b1;d=1'b1;
#20
a=1'b1;b=1'b0;c=1'b0;d=1'b0;
#20 
a=1'b1;b=1'b0;c=1'b0;d=1'b1;
#20  
a=1'b1;b=1'b0;c=1'b1;d=1'b0;
#20  
a=1'b1;b=1'b0;c=1'b1;d=1'b1;
#20  
a=1'b1;b=1'b1;c=1'b0;d=1'b0;
#20  
a=1'b1;b=1'b1;c=1'b0;d=1'b1;
#20  
a=1'b1;b=1'b1;c=1'b1;d=1'b0;
#20  
a=1'b1;b=1'b1;c=1'b1;d=1'b1;
#20  
$display("test complete");
end
endmodule

DIGITAL_SYSTEM_LAB/lab3/Q4/q4_tb.vcd
$date
	Thu Aug 28 16:01:36 2025
$end
$version
	Icarus Verilog
$end
$timescale
	1ns
$end
$scope module q4_tb $end
$var wire 1 ! f $end
$var reg 1 " a $end
$var reg 1 # b $end
$var reg 1 $ c $end
$var reg 1 % d $end
$scope module q1 $end
$var wire 1 " a $end
$var wire 1 # b $end
$var wire 1 $ c $end
$var wire 1 % d $end
$var wire 1 ! f $end
$upscope $end
$upscope $end
$enddefinitions $end
$comment Show the parameter values. $end
$dumpall
$end
#0
$dumpvars
0%
0$
0#
0"
1!
$end
#20
1%
#40
0%
1$
#60
1%
#80
0!
0%
0$
1#
#100
1!
1%
#120
0!
0%
1$
#140
1!
1%
#160
0%
0$
0#
1"
#180
0!
1%
#200
1!
0%
1$
#220
0!
1%
#240
0%
0$
1#
#260
0!
1%
#280
0%
1$
#300
0!
1%
