DIGITAL_SYSTEM_LAB/lab2/Q1/a/q1.v
module q1(a,b,c,d,f);
input a,b,c,d;
output f;
assign f=(~a&b)|(~b&c)|(c&d)|(b&~c&~d);
endmodule

DIGITAL_SYSTEM_LAB/lab2/Q2/a/q1_tb.v
`timescale 1ns/1ns
`include "q1.v"
module q1_tb();
reg a,b,c,d;
wire f;
q1 q1(a,b,c,d,f);
initial
begin
  $dumpfile("q1_tb.vcd");
  $dumpvars(0,q1_tb);
a=1'b0;b=1'b0;c=1'b0;d=1'b0;
#20  
a=1'b0;b=1'b0;c=1'b0;d=1'b1;
#20  
a=1'b0;b=1'b0;c=1'b1;d=1'b0;
#20  
a=1'b0;b=1'b0;c=1'b1;d=1'b1;
#20  
a=1'b0;b=1'b1;c=1'b0;d=1'b0;
#20  
a=1'b0;b=1'b1;c=1'b0;d=1'b1;
#20  
a=1'b0;b=1'b1;c=1'b1;d=1'b0;
#20  
a=1'b0;b=1'b1;c=1'b1;d=1'b1;
#20
a=1'b1;b=1'b0;c=1'b0;d=1'b0;
#20 
a=1'b1;b=1'b0;c=1'b0;d=1'b1;
#20  
a=1'b1;b=1'b0;c=1'b1;d=1'b0;
#20  
a=1'b1;b=1'b0;c=1'b1;d=1'b1;
#20  
a=1'b1;b=1'b1;c=1'b0;d=1'b0;
#20  
a=1'b1;b=1'b1;c=1'b0;d=1'b1;
#20  
a=1'b1;b=1'b1;c=1'b1;d=1'b0;
#20  
a=1'b1;b=1'b1;c=1'b1;d=1'b1;
#20  
$display("test complete");
end
endmodule

DIGITAL_SYSTEM_LAB/lab2/Q1/a/q1_tb.vcd
$date
	Sat Aug 16 18:15:04 2025
$end
$version
	Icarus Verilog
$end
$timescale
	1ns
$end
$scope module q1_tb $end
$var wire 1 ! f $end
$var reg 1 " a $end
$var reg 1 # b $end
$var reg 1 $ c $end
$var reg 1 % d $end
$scope module q1 $end
$var wire 1 " a $end
$var wire 1 # b $end
$var wire 1 $ c $end
$var wire 1 % d $end
$var wire 1 ! f $end
$upscope $end
$upscope $end
$enddefinitions $end
$comment Show the parameter values. $end
$dumpall
$end
#0
$dumpvars
0%
0$
0#
0"
0!
$end
#20
1%
#40
1!
0%
1$
#60
1%
#80
0%
0$
1#
#100
1%
#120
0%
1$
#140
1%
#160
0!
0%
0$
0#
1"
#180
1%
#200
1!
0%
1$
#220
1%
#240
0%
0$
1#
#260
0!
1%
#280
0%
1$
#300
1!
1%
