DIGITAL_SYSTEM_LAB/lab1/q1/q1a/q1a.v
module q1a(a,b,c,d,f);
input a,b,c,d;
output f;
and(andab_op,a,b);
or(orc_op,andab_op,c);
not(not_op,orc_op);
and(and_out,not_op,d);
or(or_op,andab_op,d);
and(f,and_out,or_op);
endmodule

DIGITAL_SYSTEM_LAB/lab1/q1/q1a/q1a_tb.v
`timescale 1ns/1ns
`include "q1a.v"
module q1a_tb();
reg a,b,c,d;
wire f;
q1a q1(a,b,c,d,f);
initial
begin
  $dumpfile("q1a_tb.vcd");
  $dumpvars(0,q1a_tb);
a=1'b0;b=1'b0;c=1'b0;d=1'b0;
#20  
a=1'b0;b=1'b0;c=1'b0;d=1'b1;
#20  
a=1'b0;b=1'b0;c=1'b1;d=1'b0;
#20  
a=1'b0;b=1'b0;c=1'b1;d=1'b1;
#20  
a=1'b0;b=1'b1;c=1'b0;d=1'b0;
#20  
a=1'b0;b=1'b1;c=1'b0;d=1'b1;
#20  
a=1'b0;b=1'b1;c=1'b1;d=1'b0;
#20  
a=1'b0;b=1'b1;c=1'b1;d=1'b1;
#20
a=1'b1;b=1'b0;c=1'b0;d=1'b0;
#20 
a=1'b1;b=1'b0;c=1'b0;d=1'b1;
#20  
a=1'b1;b=1'b0;c=1'b1;d=1'b0;
#20  
a=1'b1;b=1'b0;c=1'b1;d=1'b1;
#20  
a=1'b1;b=1'b1;c=1'b0;d=1'b0;
#20  
a=1'b1;b=1'b1;c=1'b0;d=1'b1;
#20  
a=1'b1;b=1'b1;c=1'b1;d=1'b0;
#20  
a=1'b1;b=1'b1;c=1'b1;d=1'b1;
#20  
$display("test complete");
end
endmodule

DIGITAL_SYSTEM_LAB/lab1/q1/q1a/q1a_tb.vcd
$date
	Fri Aug 15 12:23:58 2025
$end
$version
	Icarus Verilog
$end
$timescale
	1ns
$end
$scope module q1a_tb $end
$var wire 1 ! f $end
$var reg 1 " a $end
$var reg 1 # b $end
$var reg 1 $ c $end
$var reg 1 % d $end
$scope module q1 $end
$var wire 1 " a $end
$var wire 1 & and_out $end
$var wire 1 ' andab_op $end
$var wire 1 # b $end
$var wire 1 $ c $end
$var wire 1 % d $end
$var wire 1 ! f $end
$var wire 1 ( not_op $end
$var wire 1 ) or_op $end
$var wire 1 * orc_op $end
$upscope $end
$upscope $end
$enddefinitions $end
$comment Show the parameter values. $end
$dumpall
$end
#0
$dumpvars
0*
0)
1(
0'
0&
0%
0$
0#
0"
0!
$end
#20
1!
1&
1)
1%
#40
0!
0(
0&
0)
1*
0%
1$
#60
1)
1%
#80
1(
0)
0*
0%
0$
1#
#100
1!
1&
1)
1%
#120
0!
0(
0&
0)
1*
0%
1$
#140
1)
1%
#160
1(
0)
0*
0%
0$
0#
1"
#180
1!
1&
1)
1%
#200
0!
0(
0&
0)
1*
0%
1$
#220
1)
1%
#240
1'
0%
0$
1#
#260
1%
#280
0%
1$
#300
1%
